[
  {
    "id": 1,
    "destacado": false,
    "nombre": "Calza",
    "marca": "Adidas",
    "material": "lycra",
    "talle": 1,
    "precio": 2500,
    "cantidad": 1,
    "img": "../image/fotos_productos/calza_negra.jpg"
  },
  {
    "id": 2,
    "destacado": false,
    "nombre": "Calza",
    "marca": "Adidas",
    "material": "lycra",
    "talle": 2,
    "precio": 2500,
    "cantidad": 1,
    "img": "../image/fotos_productos/calza_negra.jpg"
  },
  {
    "id": 3,
    "destacado": false,
    "nombre": "Calza",
    "marca": "Adidas",
    "material": "lycra",
    "talle": 3,
    "precio": 2500,
    "cantidad": 1,
    "img": "../image/fotos_productos/calza_negra.jpg"
  },
  {
    "id": 4,
    "destacado": false,
    "nombre": "Calza",
    "marca": "Adidas",
    "material": "lycra",
    "talle": 4,
    "precio": 2500,
    "cantidad": 1,
    "img": "../image/fotos_productos/calza_negra.jpg"
  },
  {
    "id": 5,
    "destacado": false,
    "nombre": "Calza",
    "marca": "Adidas",
    "material": "lycra",
    "talle": 5,
    "precio": 2500,
    "cantidad": 1,
    "img": "../image/fotos_productos/calza_negra.jpg"
  },
  {
    "id": 6,
    "destacado": false,
    "nombre": "Calza",
    "marca": "Adidas",
    "material": "lycra",
    "talle": 6,
    "precio": 2500,
    "cantidad": 1,
    "img": "../image/fotos_productos/calza_negra.jpg"
  },
  {
    "id": 7,
    "destacado": false,
    "nombre": "Calza corta",
    "marca": "Romabella",
    "material": "lycra",
    "talle": 1,
    "precio": 2000,
    "cantidad": 1,
    "img": "../image/fotos_productos/calza_corta.jpg"
  },
  {
    "id": 8,
    "destacado": false,
    "nombre": "Calza corta",
    "marca": "Romabella",
    "material": "lycra",
    "talle": 2,
    "precio": 2000,
    "cantidad": 1,
    "img": "../image/fotos_productos/calza_corta.jpg"
  },
  {
    "id": 9,
    "destacado": false,
    "nombre": "Calza corta",
    "marca": "Romabella",
    "material": "lycra",
    "talle": 3,
    "precio": 2000,
    "cantidad": 1,
    "img": "../image/fotos_productos/calza_corta.jpg"
  },
  {
    "id": 10,
    "destacado": true,
    "nombre": "Calza corta",
    "marca": "Romabella",
    "material": "lycra",
    "talle": 4,
    "precio": 2000,
    "cantidad": 1,
    "img": "../image/fotos_productos/calza_corta.jpg"
  },
  {
    "id": 11,
    "destacado": false,
    "nombre": "Calza corta",
    "marca": "Romabella",
    "material": "lycra",
    "talle": 5,
    "precio": 2000,
    "cantidad": 1,
    "img": "../image/fotos_productos/calza_corta.jpg"
  },
  {
    "id": 12,
    "destacado": false,
    "nombre": "Calza corta",
    "marca": "Romabella",
    "material": "lycra",
    "talle": 6,
    "precio": 2000,
    "cantidad": 1,
    "img": "../image/fotos_productos/calza_corta.jpg"
  },
  {
    "id": 13,
    "destacado": false,
    "nombre": "Pantalon",
    "marca": "Romabella",
    "material": "algodon",
    "talle": 36,
    "precio": 2200,
    "cantidad": 1,
    "img": "../image/fotos_productos/pantalon_rosa.jpg"
  },
  {
    "id": 14,
    "destacado": false,
    "nombre": "Pantalon",
    "marca": "Romabella",
    "material": "algodon",
    "talle": 38,
    "precio": 2200,
    "cantidad": 1,
    "img": "../image/fotos_productos/pantalon_rosa.jpg"
  },
  {
    "id": 15,
    "destacado": false,
    "nombre": "Pantalon",
    "marca": "Romabella",
    "material": "algodon",
    "talle": 40,
    "precio": 2200,
    "cantidad": 1,
    "img": "../image/fotos_productos/pantalon_rosa.jpg"
  },
  {
    "id": 16,
    "destacado": false,
    "nombre": "Pantalon",
    "marca": "Romabella",
    "material": "algodon",
    "talle": 42,
    "precio": 2200,
    "cantidad": 1,
    "img": "../image/fotos_productos/pantalon_rosa.jpg"
  },
  {
    "id": 17,
    "destacado": false,
    "nombre": "Pantalon",
    "marca": "Romabella",
    "material": "algodon",
    "talle": 44,
    "precio": 2200,
    "cantidad": 1,
    "img": "../image/fotos_productos/pantalon_rosa.jpg"
  },
  {
    "id": 18,
    "destacado": false,
    "nombre": "Pantalon",
    "marca": "Romabella",
    "material": "algodon",
    "talle": 46,
    "precio": 2200,
    "cantidad": 1,
    "img": "../image/fotos_productos/pantalon_rosa.jpg"
  },
  {
    "id": 19,
    "destacado": false,
    "nombre": "Pantalon",
    "marca": "Romabella",
    "material": "algodon",
    "talle": 48,
    "precio": 2200,
    "cantidad": 1,
    "img": "../image/fotos_productos/pantalon_rosa.jpg"
  },
  {
    "id": 20,
    "destacado": false,
    "nombre": "Pantalon y blusa",
    "marca": "Romabella",
    "material": "algodon",
    "talle": "S",
    "precio": 5000,
    "cantidad": 1,
    "img": "../image/fotos_productos/pantalon_y_blusa.jpg"
  },
  {
    "id": 21,
    "destacado": false,
    "nombre": "Pantalon y blusa",
    "marca": "Romabella",
    "material": "algodon",
    "talle": "M",
    "precio": 5000,
    "cantidad": 1,
    "img": "../image/fotos_productos/pantalon_y_blusa.jpg"
  },
  {
    "id": 22,
    "destacado": false,
    "nombre": "Pantalon y blusa",
    "marca": "Romabella",
    "material": "algodon",
    "talle": "L",
    "precio": 5000,
    "cantidad": 1,
    "img": "../image/fotos_productos/pantalon_y_blusa.jpg"
  },
  {
    "id": 23,
    "destacado": false,
    "nombre": "Pantalon y blusa",
    "marca": "Romabella",
    "material": "algodon",
    "talle": "XL",
    "precio": 5000,
    "cantidad": 1,
    "img": "../image/fotos_productos/pantalon_y_blusa.jpg"
  },
  {
    "id": 24,
    "destacado": false,
    "nombre": "Conjunto gris",
    "marca": "Romabella",
    "material": "algodon",
    "talle": "S",
    "precio": 5000,
    "cantidad": 1,
    "img": "../image/fotos_productos/conjunto_gris.jpg"
  },
  {
    "id": 25,
    "destacado": false,
    "nombre": "Conjunto gris",
    "marca": "Romabella",
    "material": "algodon",
    "talle": "M",
    "precio": 5000,
    "cantidad": 1,
    "img": "../image/fotos_productos/conjunto_gris.jpg"
  },
  {
    "id": 26,
    "destacado": false,
    "nombre": "Conjunto gris",
    "marca": "Romabella",
    "material": "algodon",
    "talle": "L",
    "precio": 5000,
    "cantidad": 1,
    "img": "../image/fotos_productos/conjunto_gris.jpg"
  },
  {
    "id": 27,
    "destacado": false,
    "nombre": "Conjunto gris",
    "marca": "Romabella",
    "material": "algodon",
    "talle": "XL",
    "precio": 5000,
    "cantidad": 1,
    "img": "../image/fotos_productos/conjunto_gris.jpg"
  },
  {
    "id": 28,
    "destacado": false,
    "nombre": "Vestido claro",
    "marca": "Romabella",
    "material": "algodon",
    "talle": 1,
    "precio": 6000,
    "cantidad": 1,
    "img": "../image/fotos_productos/vestido_claro.jpg"
  },
  {
    "id": 29,
    "destacado": false,
    "nombre": "Vestido claro",
    "marca": "Romabella",
    "material": "algodon",
    "talle": 2,
    "precio": 6000,
    "cantidad": 1,
    "img": "../image/fotos_productos/vestido_claro.jpg"
  },
  {
    "id": 30,
    "destacado": false,
    "nombre": "Vestido claro",
    "marca": "Romabella",
    "material": "algodon",
    "talle": 3,
    "precio": 6000,
    "cantidad": 1,
    "img": "../image/fotos_productos/vestido_claro.jpg"
  },
  {
    "id": 31,
    "destacado": false,
    "nombre": "Vestido claro",
    "marca": "Romabella",
    "material": "algodon",
    "talle": 4,
    "precio": 6000,
    "cantidad": 1,
    "img": "../image/fotos_productos/vestido_claro.jpg"
  },
  {
    "id": 32,
    "destacado": false,
    "nombre": "Vestido claro",
    "marca": "Romabella",
    "material": "algodon",
    "talle": 5,
    "precio": 6000,
    "cantidad": 1,
    "img": "../image/fotos_productos/vestido_claro.jpg"
  },
  {
    "id": 33,
    "destacado": false,
    "nombre": "Vestido ocuro",
    "marca": "Romabella",
    "material": "algodon",
    "talle": 1,
    "precio": 6000,
    "cantidad": 1,
    "img": "../image/fotos_productos/vestido_oscuro.jpg"
  },
  {
    "id": 34,
    "destacado": true,
    "nombre": "Vestido ocuro",
    "marca": "Romabella",
    "material": "algodon",
    "talle": 2,
    "precio": 6000,
    "cantidad": 1,
    "img": "../image/fotos_productos/vestido_oscuro.jpg"
  },
  {
    "id": 35,
    "destacado": false,
    "nombre": "Vestido ocuro",
    "marca": "Romabella",
    "material": "algodon",
    "talle": 3,
    "precio": 6000,
    "cantidad": 1,
    "img": "../image/fotos_productos/vestido_oscuro.jpg"
  },
  {
    "id": 36,
    "destacado": false,
    "nombre": "Vestido ocuro",
    "marca": "Romabella",
    "material": "algodon",
    "talle": 4,
    "precio": 6000,
    "cantidad": 1,
    "img": "../image/fotos_productos/vestido_oscuro.jpg"
  },
  {
    "id": 37,
    "destacado": false,
    "nombre": "Vestido ocuro",
    "marca": "Romabella",
    "material": "algodon",
    "talle": 5,
    "precio": 6000,
    "cantidad": 1,
    "img": "../image/fotos_productos/vestido_oscuro.jpg"
  },
  {
    "id": 38,
    "destacado": false,
    "nombre": "Conjunto rosa",
    "marca": "Romabella",
    "material": "algodon",
    "talle": "S",
    "precio": 5000,
    "cantidad": 1,
    "img": "../image/fotos_productos/conjunto_rosa.jpg"
  },
  {
    "id": 39,
    "destacado": false,
    "nombre": "Conjunto rosa",
    "marca": "Romabella",
    "material": "algodon",
    "talle": "M",
    "precio": 5000,
    "cantidad": 1,
    "img": "../image/fotos_productos/conjunto_rosa.jpg"
  },
  {
    "id": 40,
    "destacado": true,
    "nombre": "Conjunto rosa",
    "marca": "Romabella",
    "material": "algodon",
    "talle": "L",
    "precio": 5000,
    "cantidad": 1,
    "img": "../image/fotos_productos/conjunto_rosa.jpg"
  },
  {
    "id": 41,
    "destacado": false,
    "nombre": "Conjunto rosa",
    "marca": "Romabella",
    "material": "algodon",
    "talle": "XL",
    "precio": 5000,
    "cantidad": 1,
    "img": "../image/fotos_productos/conjunto_rosa.jpg"
  }
    ]
